snaildb/__init__.py
snaildb/snaildb.py
snailDB-0.0.3.dist-info/LICENCE
snailDB-0.0.3.dist-info/METADATA
snailDB-0.0.3.dist-info/WHEEL
snailDB-0.0.3.dist-info/top_level.txt
snailDB-0.0.3.dist-info/RECORD
