Metadata-Version: 2.1
Name: snailDB
Version: 0.0.3
Summary: SnailDB, a lightweight, non-SQL database for Python.
Home-page: https://github.com/cyberkutti-iedc/snailDB
Author: Sreeraj V Rajesh
Author-email: cyberkutti@gmail.com
License: MIT
Platform: any
Classifier: Development Status :: 3 - Alpha
Classifier: Intended Audience :: Developers
Classifier: License :: OSI Approved :: MIT License
Classifier: Programming Language :: Python :: 3
Classifier: Programming Language :: Python :: 3.6
Classifier: Programming Language :: Python :: 3.7
Classifier: Programming Language :: Python :: 3.8
Classifier: Programming Language :: Python :: 3.9
Classifier: Programming Language :: Python :: 3.10
License-File: LICENCE
Requires-Dist: Flask
